{
    "authors": [
        {
            "id": "pradeep-dhakal",
            "name": "Pradeep Dhakal",
            "photo": "https://findjobsinfinland.fi/images/pradeep-dhakal.png"
        },
        {
            "id": "prasiddha-acharya",
            "name": "Prasiddha Acharya",
            "photo": "https://findjobsinfinland.fi/images/prasiddha-acharya.png"
        },
        {
            "id": "binam-bhandari",
            "name": "Binam Bhandari",
            "photo": "https://findjobsinfinland.fi/images/binam-bhandari.png"
        },
        {
            "id": "prem-tamang",
            "name": "Prem Tamang",
            "photo": "https://findjobsinfinland.fi/images/prem-tamang.png"
        },
        {
            "id": "aayush-guragain",
            "name": "Aayush Guragain",
            "photo": "https://findjobsinfinland.fi/images/aayush-guragain.png"
        },
        {
            "id": "anam-neupane",
            "name": "Anam Neupane",
            "photo": "https://findjobsinfinland.fi/images/anam-neupane.png"
        }
    ]
}